rfremoterunner/__init__.py
rfremoterunner/agent.py
rfremoterunner/executor.py
rfremoterunner/executor_argparser.py
rfremoterunner/rf_client.py
rfremoterunner/rf_server.py
rfremoterunner/utils.py
robotframework_remoterunner-2.0.0.dist-info/LICENSE
robotframework_remoterunner-2.0.0.dist-info/METADATA
robotframework_remoterunner-2.0.0.dist-info/WHEEL
robotframework_remoterunner-2.0.0.dist-info/entry_points.txt
robotframework_remoterunner-2.0.0.dist-info/top_level.txt
robotframework_remoterunner-2.0.0.dist-info/RECORD
