Metadata-Version: 2.1
Name: robotframework-remoterunner
Version: 2.0.0
Summary: A library that provides the ability to execute RobotFramework test suites on a remote host.
Home-page: https://github.com/chrisBrookes93/robotframework-remoterunner
Author: Chris Brookes
Author-email: chris-brookes93@outlook.com
License: MIT
Project-URL: Issue Tracker, https://github.com/chrisBrookes93/robotframework-remoterunner/issues
Project-URL: Repository, https://github.com/chrisBrookes93/robotframework-remoterunner
Keywords: robotframework automation testautomation rpa testing acceptancetesting atdd bdd
Platform: UNKNOWN
Classifier: Development Status :: 6 - Mature
Classifier: Intended Audience :: Developers
Classifier: License :: OSI Approved :: MIT License
Classifier: Operating System :: OS Independent
Classifier: Programming Language :: Python :: 2
Classifier: Programming Language :: Python :: 2.7
Classifier: Programming Language :: Python :: 3
Classifier: Programming Language :: Python :: 3.6
Classifier: Programming Language :: Python :: 3.7
Classifier: Programming Language :: Python :: 3.8
Classifier: Programming Language :: Python :: 3.9
Classifier: Programming Language :: Python :: Implementation :: CPython
Classifier: Framework :: Robot Framework
Classifier: Topic :: Software Development :: Testing
Requires-Python: >=2.7
Requires-Dist: robotframework (>=3.1.1)
Requires-Dist: six
Provides-Extra: codecov
Requires-Dist: coverage (==5.3.1) ; extra == 'codecov'
Requires-Dist: pylint (==2.6.0) ; extra == 'codecov'
Provides-Extra: dev
Requires-Dist: unittest2 (==1.1.0) ; extra == 'dev'
Requires-Dist: mock (==3.0.5) ; extra == 'dev'
